_dev/pinball.py
_dev/old_version/basic_simulation.py
_dev/old_version/classes.py
_dev/old_version/general_simulation.py
_dev/old_version/learning_classes.py
_dev/old_version/legacy_csv_writers.py
_dev/old_version/pedestrian.py
_dev/old_version/test_funcanimation.py
_dev/sandbox/streamlit_test.py
bengine-1.0.0.dist-info/licenses/LICENSE.txt
simulation_engine/__init__.py
simulation_engine/core/__init__.py
simulation_engine/core/environment.py
simulation_engine/core/manager.py
simulation_engine/core/particle.py
simulation_engine/main/__init__.py
simulation_engine/main/entrypoint.py
simulation_engine/types/__init__.py
simulation_engine/types/birds.py
simulation_engine/types/evac.py
simulation_engine/types/nbody.py
simulation_engine/types/pool.py
simulation_engine/types/springs.py
simulation_engine/utils/__init__.py
simulation_engine/utils/errors.py
simulation_engine/utils/help.py
tests/__init__.py
tests/test_input_args.py
tests/test_integration.py
bengine-1.0.0.dist-info/METADATA
bengine-1.0.0.dist-info/WHEEL
bengine-1.0.0.dist-info/entry_points.txt
bengine-1.0.0.dist-info/top_level.txt
bengine-1.0.0.dist-info/RECORD
