Metadata-Version: 2.4
Name: bengine
Version: 1.0.0
Summary: General physics engine for force-based particle simulations. Run `bengine -h` for CLI options.
Author-email: Ben Winstanley <benjamin.winstanley.007@gmail.com>
License: MIT
Requires-Python: >=3.9
License-File: LICENSE.txt
Requires-Dist: matplotlib==3.9.4
Requires-Dist: numpy==2.0.2
Requires-Dist: opencv-python==4.11.0.86
Requires-Dist: pathvalidate==3.2.3
Requires-Dist: rich==14.0.0
Requires-Dist: tqdm==4.67.1
Dynamic: license-file
